<SYNSETS>
<SYNSET><ID>TUR10-0001070</ID><SYNONYM><LITERAL>keraksiz<SENSE>2</SENSE></LITERAL></SYNONYM><POS>a</POS><DEF>Keraksiz, keraksiz, keraksiz, bo'sh</DEF></SYNSET>
<SYNSET><ID>TUR10-0003580</ID><SYNONYM><LITERAL>qobiliyatsiz<SENSE>3</SENSE></LITERAL></SYNONYM><POS>a</POS><DEF>Unga kamtarin odam tomonidan berilgan muqaddas joy</DEF><EXAMPLE>Biraz sonra Gazi yanına seryaveri Salih Bey'in yaveri Muzaffer Bey'i ve âcizi alarak otomobile bindi.</EXAMPLE></SYNSET>
<SYNSET><ID>TUR10-0000220</ID><SYNONYM><LITERAL>abajurli<SENSE>1</SENSE></LITERAL></SYNONYM><POS>a</POS><SR>TUR10-0000230<TYPE>ANTONYM</TYPE></SR><SR>TUR10-0000180<TYPE>DERIVATION_RELATED</TYPE></SR><SR>TUR10-0000190<TYPE>DERIVATION_RELATED</TYPE></SR><DEF>abajur bilan</DEF><EXAMPLE>Üstünde lacivert abajurlu, parlak bir madenden lamba.</EXAMPLE></SYNSET>
<SYNSET><ID>TUR10-0000230</ID><SYNONYM><LITERAL>abajursiz<SENSE>1</SENSE></LITERAL></SYNONYM><POS>a</POS><SR>TUR10-0000220<TYPE>ANTONYM</TYPE></SR><SR>TUR10-0000180<TYPE>DERIVATION_RELATED</TYPE></SR><SR>TUR10-0000190<TYPE>DERIVATION_RELATED</TYPE></SR><DEF>abajursiz</DEF><EXAMPLE>Tavandaki abajursuz, çelik elektrik lambasını yakmış okuyordu.</EXAMPLE></SYNSET>
<SYNSET><ID>TUR10-0000260</ID><SYNONYM><LITERAL>kigizli<SENSE>1</SENSE></LITERAL></SYNONYM><POS>a</POS><SR>TUR10-0000070<TYPE>DERIVATION_RELATED</TYPE></SR><SR>TUR10-0000090<TYPE>DERIVATION_RELATED</TYPE></SR><DEF>aba kiyish</DEF></SYNSET>
<SYNSET><ID>TUR10-0000880</ID><SYNONYM><LITERAL>tahoratli<SENSE>1</SENSE></LITERAL></SYNONYM><POS>a</POS><SR>TUR10-0000830<TYPE>DERIVATION_RELATED</TYPE></SR><DEF>Wudu</DEF></SYNSET>
<SYNSET><ID>TUR10-0000890</ID><SYNONYM><LITERAL>tahoratli<SENSE>2</SENSE></LITERAL></SYNONYM><POS>a</POS><SR>TUR10-0000830<TYPE>DERIVATION_RELATED</TYPE></SR><SR>TUR10-0000840<TYPE>DERIVATION_RELATED</TYPE></SR><DEF>Tahorati buzilmagan kishi</DEF></SYNSET>
<SYNSET><ID>TUR10-0000910</ID><SYNONYM><LITERAL>tahoratlik<SENSE>2</SENSE></LITERAL></SYNONYM><POS>a</POS><SR>TUR10-0000830<TYPE>DERIVATION_RELATED</TYPE></SR><DEF>Tahorat olish uchun ishlatiladi</DEF></SYNSET>
<SYNSET><ID>TUR10-0000940</ID><SYNONYM><LITERAL>tahoratsiz<SENSE>1</SENSE></LITERAL></SYNONYM><POS>a</POS><SR>TUR10-0000830<TYPE>DERIVATION_RELATED</TYPE></SR><DEF>Tahorat olmagan kishi</DEF></SYNSET>
<SYNSET><ID>TUR10-0000950</ID><SYNONYM><LITERAL>tahoratsiz<SENSE>2</SENSE></LITERAL></SYNONYM><POS>a</POS><SR>TUR10-0000830<TYPE>DERIVATION_RELATED</TYPE></SR><DEF>Tahorati buzilgan kishi</DEF></SYNSET>
<SYNSET><ID>TUR10-0001060</ID><SYNONYM><LITERAL>bema'ni<SENSE>1</SENSE></LITERAL></SYNONYM><POS>a</POS><ILR>ENG31-01433985-s<TYPE>SYNONYM</TYPE></ILR><DEF>Aql va haqiqatdan farqli o'laroq</DEF></SYNSET>
<SYNSET><ID>TUR10-0001070</ID><SYNONYM><LITERAL>keraksiz<SENSE>2</SENSE></LITERAL></SYNONYM><POS>a</POS><DEF>Keraksiz, keraksiz, keraksiz, bo'sh</DEF></SYNSET>
<SYNSET><ID>TUR10-0001260</ID><SYNONYM><LITERAL>tombul<SENSE>2</SENSE></LITERAL></SYNONYM><POS>a</POS><SR>TUR10-0001270<TYPE>DERIVATION_RELATED</TYPE></SR><DEF>Bunday yuz</DEF></SYNSET>
<SYNSET><ID>TUR10-0001390</ID><SYNONYM><LITERAL>obunalik<SENSE>2</SENSE></LITERAL></SYNONYM><POS>a</POS><SR>TUR10-0001350<TYPE>DERIVATION_RELATED</TYPE></SR><SR>TUR10-0001360<TYPE>DERIVATION_RELATED</TYPE></SR><DEF>Abonentlar yoki abonentlar uchun mavjud</DEF></SYNSET>
<SYNSET><ID>TUR10-0001500</ID><SYNONYM><LITERAL>chipor<SENSE>1</SENSE></LITERAL></SYNONYM><POS>a</POS><ILR>ENG31-01792782-s<TYPE>SYNONYM</TYPE></ILR><DEF>Piebald ko'rdi</DEF><EXAMPLE>Abraş at.</EXAMPLE></SYNSET>
<SYNSET><ID>TUR10-0001510</ID><SYNONYM><LITERAL>chipor<SENSE>2</SENSE></LITERAL></SYNONYM><POS>a</POS><DEF>Xlorofill yo'qligi sababli engil dog'lar bilan o'simlik bargi</DEF></SYNSET>
<SYNSET><ID>TUR10-0001520</ID><SYNONYM><LITERAL>chipor<SENSE>3</SENSE></LITERAL></SYNONYM><POS>a</POS><DEF>Egri, qiyshiq, notekis</DEF></SYNSET>
<SYNSET><ID>TUR10-0001530</ID><SYNONYM><LITERAL>chipor<SENSE>4</SENSE></LITERAL></SYNONYM><POS>a</POS><DEF>Teskari, qo'pol, yashirin</DEF></SYNSET>
<SYNSET><ID>TUR10-0001540</ID><SYNONYM><LITERAL>chipor<SENSE>5</SENSE></LITERAL></SYNONYM><POS>a</POS><DEF>Sepkli, qovurilgan, och ko'zli, xoch</DEF></SYNSET>
<SYNSET><ID>TUR10-0001820</ID><SYNONYM><LITERAL>jasur<SENSE>2</SENSE></LITERAL></SYNONYM><POS>a</POS><SR>TUR10-0001870<TYPE>DERIVATION_RELATED</TYPE></SR><DEF>Kuchli va zukko, epchil, baquvvat</DEF><EXAMPLE>Bunlar yarının kadın hakları savunucuları, acar avukatları olacak soydandırlar.</EXAMPLE></SYNSET>
<SYNSET><ID>TUR10-0001830</ID><SYNONYM><LITERAL>kuchli<SENSE>3</SENSE></LITERAL><LITERAL>gıcır<SENSE>2</SENSE></LITERAL><LITERAL>cedit<SENSE>1</SENSE></LITERAL><LITERAL>çiçeği burnunda<SENSE>1</SENSE></LITERAL></SYNONYM><POS>a</POS><SR>TUR10-0252760<TYPE>DERIVATION_RELATED</TYPE></SR><SR>TUR10-1256450<TYPE>DERIVATION_RELATED</TYPE></SR><DEF>Yangi</DEF></SYNSET>
<SYNSET><ID>TUR10-0002530</ID><SYNONYM><LITERAL>achchiq<SENSE>5</SENSE></LITERAL></SYNONYM><POS>a</POS><DEF>To'q rang</DEF></SYNSET>
<SYNSET><ID>TUR10-0002540</ID><SYNONYM><LITERAL>achchiq<SENSE>6</SENSE></LITERAL></SYNONYM><POS>a</POS><ILR>ENG31-02407331-s<TYPE>SYNONYM</TYPE></ILR><SR>TUR10-0002660<TYPE>DERIVATION_RELATED</TYPE></SR><SR>TUR10-0003470<TYPE>DERIVATION_RELATED</TYPE></SR><SR>TUR10-1192410<TYPE>DERIVATION_RELATED</TYPE></SR><DEF>O'tkir, yoqimsiz, zo'ravonlik</DEF><EXAMPLE>Acı poyraz kuvvetle esiyordu.</EXAMPLE></SYNSET>
<SYNSET><ID>TUR10-0002550</ID><SYNONYM><LITERAL>qayg'uli<SENSE>1</SENSE></LITERAL><LITERAL>acı<SENSE>7</SENSE></LITERAL><LITERAL>belalı<SENSE>1</SENSE></LITERAL><LITERAL>can sıkıcı<SENSE>1</SENSE></LITERAL><LITERAL>cehennemi<SENSE>2</SENSE></LITERAL><LITERAL>cehennemî<SENSE>2</SENSE></LITERAL><LITERAL>fena<SENSE>2</SENSE></LITERAL><LITERAL>müessif<SENSE>1</SENSE></LITERAL></SYNONYM><POS>a</POS><SR>TUR10-0811860<TYPE>DERIVATION_RELATED</TYPE></SR><SR>TUR10-0090160<TYPE>DERIVATION_RELATED</TYPE></SR><SR>TUR10-0134600<TYPE>DERIVATION_RELATED</TYPE></SR><SR>TUR10-0002660<TYPE>DERIVATION_RELATED</TYPE></SR><SR>TUR10-0112370<TYPE>DERIVATION_RELATED</TYPE></SR><SR>TUR10-0267650<TYPE>DERIVATION_RELATED</TYPE></SR><SR>TUR10-0917560<TYPE>DERIVATION_RELATED</TYPE></SR><SR>TUR10-0917570<TYPE>DERIVATION_RELATED</TYPE></SR><SR>TUR10-1191650<TYPE>DERIVATION_RELATED</TYPE></SR><SR>TUR10-1192410<TYPE>DERIVATION_RELATED</TYPE></SR><DEF>Achinarli, qayg'uli</DEF></SYNSET>
<SYNSET><ID>TUR10-0002770</ID><SYNONYM><LITERAL>achinarli<SENSE>1</SENSE></LITERAL></SYNONYM><POS>a</POS><ILR>ENG31-00908403-s<TYPE>SYNONYM</TYPE></ILR><DEF>Achinarli, og'riqli, ta'sirli, g'amgin, qorong'u</DEF><EXAMPLE>Bu âdet bir fabrika sahibinin acıklı hayat hikâyesiyle birlikte kondulara yayıldı.</EXAMPLE></SYNSET>
<SYNSET><ID>TUR10-0002780</ID><SYNONYM><LITERAL>fojeali<SENSE>2</SENSE></LITERAL></SYNONYM><POS>a</POS><ILR>ENG31-01369441-s<TYPE>SYNONYM</TYPE></ILR><DEF>Og'riqli, g'amgin va qayg'uli</DEF><EXAMPLE>Kendimi bu acı ve acıklı kitlenin bir parçası gibi hissediyordum.</EXAMPLE></SYNSET>
<SYNSET><ID>TUR10-0003110</ID><SYNONYM><LITERAL>shafqatsiz<SENSE>1</SENSE></LITERAL><LITERAL>allahsız<SENSE>1</SENSE></LITERAL><LITERAL>gaddar<SENSE>1</SENSE></LITERAL><LITERAL>amansız<SENSE>1</SENSE></LITERAL><LITERAL>duygusuz<SENSE>2</SENSE></LITERAL><LITERAL>biaman<SENSE>1</SENSE></LITERAL><LITERAL>ceberut<SENSE>4</SENSE></LITERAL><LITERAL>cani<SENSE>2</SENSE></LITERAL><LITERAL>taş kalpli<SENSE>1</SENSE></LITERAL><LITERAL>taş yürekli<SENSE>1</SENSE></LITERAL><LITERAL>tiran<SENSE>2</SENSE></LITERAL><LITERAL>zalim<SENSE>1</SENSE></LITERAL><LITERAL>vicdansız<SENSE>1</SENSE></LITERAL><LITERAL>gavur<SENSE>3</SENSE></LITERAL><LITERAL>gâvur<SENSE>3</SENSE></LITERAL><LITERAL>imanı yok<SENSE>1</SENSE></LITERAL><LITERAL>imansız<SENSE>2</SENSE></LITERAL><LITERAL>kalpsiz<SENSE>1</SENSE></LITERAL><LITERAL>kaskatı<SENSE>3</SENSE></LITERAL><LITERAL>katı<SENSE>2</SENSE></LITERAL><LITERAL>katı yürekli<SENSE>1</SENSE></LITERAL><LITERAL>kitapsız<SENSE>3</SENSE></LITERAL><LITERAL>kıyak<SENSE>4</SENSE></LITERAL><LITERAL>merhametsiz<SENSE>1</SENSE></LITERAL><LITERAL>moskof<SENSE>1</SENSE></LITERAL><LITERAL>insafsız<SENSE>1</SENSE></LITERAL></SYNONYM><POS>a</POS><SR>TUR10-0375860<TYPE>DERIVATION_RELATED</TYPE></SR><SR>TUR10-0536630<TYPE>DERIVATION_RELATED</TYPE></SR><SR>TUR10-0819660<TYPE>DERIVATION_RELATED</TYPE></SR><SR>TUR10-0132130<TYPE>DERIVATION_RELATED</TYPE></SR><SR>TUR10-0281330<TYPE>DERIVATION_RELATED</TYPE></SR><SR>TUR10-0284330<TYPE>DERIVATION_RELATED</TYPE></SR><SR>TUR10-0284370<TYPE>DERIVATION_RELATED</TYPE></SR><SR>TUR10-0917570<TYPE>DERIVATION_RELATED</TYPE></SR><SR>TUR10-1028890<TYPE>DERIVATION_RELATED</TYPE></SR><SR>TUR10-1191650<TYPE>DERIVATION_RELATED</TYPE></SR><SR>TUR10-1198870<TYPE>DERIVATION_RELATED</TYPE></SR><SR>TUR10-0031980<TYPE>DERIVATION_RELATED</TYPE></SR><SR>TUR10-0227400<TYPE>DERIVATION_RELATED</TYPE></SR><SR>TUR10-0405460<TYPE>DERIVATION_RELATED</TYPE></SR><SR>TUR10-0750060<TYPE>DERIVATION_RELATED</TYPE></SR><SR>TUR10-0284390<TYPE>DERIVATION_RELATED</TYPE></SR><SR>TUR10-0550900<TYPE>DERIVATION_RELATED</TYPE></SR><SR>TUR10-0550910<TYPE>DERIVATION_RELATED</TYPE></SR><DEF>Rahm-shafqat va vijdonsiz</DEF></SYNSET>
<SYNSET><ID>TUR10-0003170</ID><SYNONYM><LITERAL>ta'sirchan<SENSE>1</SENSE></LITERAL><LITERAL>acımsı<SENSE>2</SENSE></LITERAL><LITERAL>koygun<SENSE>1</SENSE></LITERAL><LITERAL>müessir<SENSE>1</SENSE></LITERAL><LITERAL>patetik<SENSE>1</SENSE></LITERAL><LITERAL>yakıcı<SENSE>3</SENSE></LITERAL><LITERAL>yanık<SENSE>7</SENSE></LITERAL></SYNONYM><POS>a</POS><SR>TUR10-0085540<TYPE>DERIVATION_RELATED</TYPE></SR><DEF>Penetratsiya</DEF></SYNSET>
<SYNSET><ID>TUR10-0003180</ID><SYNONYM><LITERAL>achchiq<SENSE>1</SENSE></LITERAL><LITERAL>acımtırak<SENSE>1</SENSE></LITERAL><LITERAL>acırak<SENSE>1</SENSE></LITERAL></SYNONYM><POS>a</POS><SR>TUR10-0002490<TYPE>DERIVATION_RELATED</TYPE></SR><SR>TUR10-0100660<TYPE>DERIVATION_RELATED</TYPE></SR><DEF>Og'riq kabi, og'riq kabi, og'riq kabi</DEF></SYNSET>
<SYNSET><ID>TUR10-0003320</ID><SYNONYM><LITERAL>og'riqsiz<SENSE>2</SENSE></LITERAL></SYNONYM><POS>a</POS><DEF>Og'riq, og'riq eshitilmagan</DEF><EXAMPLE>Acısız doğum.</EXAMPLE></SYNSET>
<SYNSET><ID>TUR10-0003560</ID><SYNONYM><LITERAL>ojiz<SENSE>1</SENSE></LITERAL><LITERAL>beli bükük<SENSE>2</SENSE></LITERAL><LITERAL>buncacık<SENSE>1</SENSE></LITERAL><LITERAL>güçsüz<SENSE>1</SENSE></LITERAL><LITERAL>kof<SENSE>3</SENSE></LITERAL><LITERAL>miskin<SENSE>4</SENSE></LITERAL><LITERAL>ruhsuz<SENSE>1</SENSE></LITERAL><LITERAL>sökel<SENSE>2</SENSE></LITERAL><LITERAL>zavallı<SENSE>2</SENSE></LITERAL><LITERAL>zebun<SENSE>1</SENSE></LITERAL><LITERAL>zayıf<SENSE>2</SENSE></LITERAL><LITERAL>baygın<SENSE>2</SENSE></LITERAL><LITERAL>süzgün<SENSE>1</SENSE></LITERAL><LITERAL>süzük<SENSE>1</SENSE></LITERAL></SYNONYM><POS>a</POS><SR>TUR10-0120760<TYPE>DERIVATION_RELATED</TYPE></SR><SR>TUR10-0100890<TYPE>DERIVATION_RELATED</TYPE></SR><SR>TUR10-0138260<TYPE>DERIVATION_RELATED</TYPE></SR><SR>TUR10-0132650<TYPE>DERIVATION_RELATED</TYPE></SR><SR>TUR10-0312300<TYPE>DERIVATION_RELATED</TYPE></SR><SR>TUR10-0498190<TYPE>DERIVATION_RELATED</TYPE></SR><SR>TUR10-0044080<TYPE>DERIVATION_RELATED</TYPE></SR><SR>TUR10-0086300<TYPE>DERIVATION_RELATED</TYPE></SR><SR>TUR10-0086310<TYPE>DERIVATION_RELATED</TYPE></SR><SR>TUR10-0312640<TYPE>DERIVATION_RELATED</TYPE></SR><SR>TUR10-1210190<TYPE>DERIVATION_RELATED</TYPE></SR><DEF>Kim o'z vazifasini bajarish uchun etarli kuchga ega emas</DEF></SYNSET>
<SYNSET><ID>TUR10-0003580</ID><SYNONYM><LITERAL>qobiliyatsiz<SENSE>3</SENSE></LITERAL></SYNONYM><POS>a</POS><DEF>Unga kamtarin odam tomonidan berilgan muqaddas joy</DEF><EXAMPLE>Biraz sonra Gazi yanına seryaveri Salih Bey'in yaveri Muzaffer Bey'i ve âcizi alarak otomobile bindi.</EXAMPLE></SYNSET>
<SYNSET><ID>TUR10-0003640</ID><SYNONYM><LITERAL>sabrsiz<SENSE>1</SENSE></LITERAL><LITERAL>acul<SENSE>1</SENSE></LITERAL><LITERAL>iveğen<SENSE>1</SENSE></LITERAL><LITERAL>içi tez<SENSE>1</SENSE></LITERAL><LITERAL>farfara<SENSE>3</SENSE></LITERAL><LITERAL>telaşlı<SENSE>2</SENSE></LITERAL><LITERAL>ivecen<SENSE>1</SENSE></LITERAL><LITERAL>sabırsız<SENSE>2</SENSE></LITERAL><LITERAL>canı tez<SENSE>1</SENSE></LITERAL><LITERAL>kıvrak<SENSE>5</SENSE></LITERAL><LITERAL>aceleci<SENSE>1</SENSE></LITERAL></SYNONYM><POS>a</POS><ILR>ENG31-00327506-s<TYPE>SYNONYM</TYPE></ILR><SR>TUR10-0001990<TYPE>DERIVATION_RELATED</TYPE></SR><SR>TUR10-0002000<TYPE>DERIVATION_RELATED</TYPE></SR><SR>TUR10-0002010<TYPE>DERIVATION_RELATED</TYPE></SR><SR>TUR10-0388690<TYPE>DERIVATION_RELATED</TYPE></SR><SR>TUR10-0456500<TYPE>DERIVATION_RELATED</TYPE></SR><SR>TUR10-0652350<TYPE>DERIVATION_RELATED</TYPE></SR><SR>TUR10-0760200<TYPE>DERIVATION_RELATED</TYPE></SR><SR>TUR10-0456440<TYPE>DERIVATION_RELATED</TYPE></SR><SR>TUR10-0456460<TYPE>DERIVATION_RELATED</TYPE></SR><DEF>Bo'ron kabi tezkor harakat, tezkor harakat, farfara</DEF><EXAMPLE>Acul bir adam.</EXAMPLE></SYNSET>
<SYNSET><ID>TUR10-0003650</ID><SYNONYM><LITERAL>shoshilinch<SENSE>2</SENSE></LITERAL></SYNONYM><POS>a</POS><DEF>Tez; tez</DEF><EXAMPLE>Geç vakit dönen zengin ve ecnebi kumarcıların acul arabalarını duymuyor.</EXAMPLE></SYNSET>
<SYNSET><ID>TUR10-0003730</ID><SYNONYM><LITERAL>och<SENSE>1</SENSE></LITERAL></SYNONYM><POS>a</POS><SR>TUR10-0219630<TYPE>ANTONYM</TYPE></SR><ILR>ENG31-01272183-a<TYPE>SYNONYM</TYPE></ILR><DEF>Ovqatlanish kerak</DEF></SYNSET>
<SYNSET><ID>TUR10-0003740</ID><SYNONYM><LITERAL>och<SENSE>2</SENSE></LITERAL></SYNONYM><POS>a</POS><DEF>Ovqat topilmayapti</DEF></SYNSET>
<SYNSET><ID>TUR10-0003750</ID><SYNONYM><LITERAL>ochko'z<SENSE>1</SENSE></LITERAL><LITERAL>aç<SENSE>3</SENSE></LITERAL><LITERAL>açgöz<SENSE>1</SENSE></LITERAL><LITERAL>cam göz<SENSE>2</SENSE></LITERAL><LITERAL>doymaz<SENSE>1</SENSE></LITERAL><LITERAL>gözü aç<SENSE>1</SENSE></LITERAL><LITERAL>gözü doymaz<SENSE>1</SENSE></LITERAL><LITERAL>haris<SENSE>1</SENSE></LITERAL><LITERAL>tamahkar<SENSE>1</SENSE></LITERAL><LITERAL>tamahkâr<SENSE>1</SENSE></LITERAL><LITERAL>uzun dişli<SENSE>1</SENSE></LITERAL></SYNONYM><POS>a</POS><SR>TUR10-0219580<TYPE>DERIVATION_RELATED</TYPE></SR><SR>TUR10-0219820<TYPE>DERIVATION_RELATED</TYPE></SR><SR>TUR10-0410320<TYPE>DERIVATION_RELATED</TYPE></SR><SR>TUR10-0742350<TYPE>DERIVATION_RELATED</TYPE></SR><SR>TUR10-0072340<TYPE>DERIVATION_RELATED</TYPE></SR><SR>TUR10-0308070<TYPE>DERIVATION_RELATED</TYPE></SR><SR>TUR10-0308080<TYPE>DERIVATION_RELATED</TYPE></SR><DEF>Mala, oziq-ovqat va ichimlik bilan to'ymaydi</DEF></SYNSET>
<SYNSET><ID>TUR10-0003760</ID><SYNONYM><LITERAL>och<SENSE>4</SENSE></LITERAL><LITERAL>arzulu<SENSE>1</SENSE></LITERAL><LITERAL>heveskar<SENSE>1</SENSE></LITERAL><LITERAL>heveskâr<SENSE>1</SENSE></LITERAL><LITERAL>hevesli<SENSE>1</SENSE></LITERAL><LITERAL>iştahlı<SENSE>2</SENSE></LITERAL><LITERAL>istekli<SENSE>1</SENSE></LITERAL><LITERAL>ayran delisi<SENSE>2</SENSE></LITERAL><LITERAL>talip<SENSE>1</SENSE></LITERAL><LITERAL>müştehi<SENSE>1</SENSE></LITERAL></SYNONYM><POS>a</POS><ILR>ENG31-02575716-a<TYPE>SYNONYM</TYPE></ILR><SR>TUR10-0340560<TYPE>ANTONYM</TYPE></SR><ILR>ENG31-00814485-a<TYPE>SYNONYM</TYPE></ILR><SR>TUR10-0364720<TYPE>DERIVATION_RELATED</TYPE></SR><SR>TUR10-0729380<TYPE>DERIVATION_RELATED</TYPE></SR><SR>TUR10-0742110<TYPE>DERIVATION_RELATED</TYPE></SR><SR>TUR10-0048420<TYPE>DERIVATION_RELATED</TYPE></SR><SR>TUR10-0205320<TYPE>DERIVATION_RELATED</TYPE></SR><DEF>Biror narsa, ish haqida xohlash yoki qiziqish</DEF></SYNSET>
<SYNSET><ID>TUR10-0003970</ID><SYNONYM><LITERAL>ochiq<SENSE>1</SENSE></LITERAL></SYNONYM><POS>a</POS><SR>TUR10-0411810<TYPE>ANTONYM</TYPE></SR><ILR>ENG31-01657344-a<TYPE>SYNONYM</TYPE></ILR><SR>TUR10-1233640<TYPE>DERIVATION_RELATED</TYPE></SR><DEF>Yopiq emas, ochilgan</DEF></SYNSET>
<SYNSET><ID>TUR10-0003980</ID><SYNONYM><LITERAL>ochiq<SENSE>2</SENSE></LITERAL><LITERAL>mâniasız<SENSE>1</SENSE></LITERAL><LITERAL>maniasız<SENSE>1</SENSE></LITERAL><LITERAL>engelsiz<SENSE>1</SENSE></LITERAL></SYNONYM><POS>a</POS><ILR>ENG31-01626483-a<TYPE>SYNONYM</TYPE></ILR><ILR>ENG31-01920489-s<TYPE>SYNONYM</TYPE></ILR><ILR>ENG31-02533823-s<TYPE>SYNONYM</TYPE></ILR><SR>TUR10-0639250<TYPE>DERIVATION_RELATED</TYPE></SR><SR>TUR10-0005180<TYPE>DERIVATION_RELATED</TYPE></SR><DEF>To'siqsiz, bepul</DEF></SYNSET>
<SYNSET><ID>TUR10-0003990</ID><SYNONYM><LITERAL>ochiq<SENSE>3</SENSE></LITERAL></SYNONYM><POS>a</POS><ILR>ENG31-00783570-s<TYPE>SYNONYM</TYPE></ILR><SR>TUR10-0665220<TYPE>DERIVATION_RELATED</TYPE></SR><DEF>Yopiq, yalang'och</DEF><EXAMPLE>Yolcuların hepsi indikten sonra Mehmet Akif göründü, beni açık başıyla selamladı.</EXAMPLE></SYNSET>
<SYNSET><ID>TUR10-0004020</ID><SYNONYM><LITERAL>ochiq<SENSE>6</SENSE></LITERAL></SYNONYM><POS>a</POS><SR>TUR10-0654990<TYPE>DERIVATION_RELATED</TYPE></SR><SR>TUR10-0700690<TYPE>DERIVATION_RELATED</TYPE></SR><DEF>Bu diapazon ham</DEF><EXAMPLE>Açık adımlarla.</EXAMPLE></SYNSET>
<SYNSET><ID>TUR10-0004040</ID><SYNONYM><LITERAL>ochiq<SENSE>8</SENSE></LITERAL></SYNONYM><POS>a</POS><ILR>ENG31-00429900-a<TYPE>SYNONYM</TYPE></ILR><SR>TUR10-0004930<TYPE>DERIVATION_RELATED</TYPE></SR><SR>TUR10-0389810<TYPE>DERIVATION_RELATED</TYPE></SR><SR>TUR10-0389830<TYPE>DERIVATION_RELATED</TYPE></SR><SR>TUR10-0793950<TYPE>DERIVATION_RELATED</TYPE></SR><SR>TUR10-0918650<TYPE>DERIVATION_RELATED</TYPE></SR><DEF>Tushunish oson, vazi</DEF><EXAMPLE>Açık konuşma zamanının artık geldiğine kani idim.</EXAMPLE></SYNSET>
<SYNSET><ID>TUR10-0004060</ID><SYNONYM><LITERAL>ochiq<SENSE>10</SENSE></LITERAL></SYNONYM><POS>a</POS><SR>TUR10-0005180<TYPE>DERIVATION_RELATED</TYPE></SR><DEF>Turli xil fikrlarga toqat qilish va ta'sirlanishiga qodir</DEF><EXAMPLE>... her çeşit kafa ve gönül fırtınalarına açık bir adamdı o.</EXAMPLE></SYNSET>
<SYNSET><ID>TUR10-0004070</ID><SYNONYM><LITERAL>ochiq<SENSE>11</SENSE></LITERAL></SYNONYM><POS>a</POS><SR>TUR10-0479090<TYPE>ANTONYM</TYPE></SR><ILR>ENG31-00410069-s<TYPE>SYNONYM</TYPE></ILR><ILR>ENG31-00409737-a<TYPE>SYNONYM</TYPE></ILR><SR>TUR10-0004850<TYPE>DERIVATION_RELATED</TYPE></SR><DEF>To'q rang emas</DEF></SYNSET>
<SYNSET><ID>TUR10-0004080</ID><SYNONYM><LITERAL>ochiq<SENSE>12</SENSE></LITERAL></SYNONYM><POS>a</POS><SR>TUR10-0389830<TYPE>DERIVATION_RELATED</TYPE></SR><SR>TUR10-0665220<TYPE>DERIVATION_RELATED</TYPE></SR><DEF>Jinsiy aloqa sahnalarini barcha yalang'ochliklari bilan tasvirlaydigan kitoblar, rasmlar, filmlar va boshqalar.</DEF></SYNSET>
<SYNSET><ID>TUR10-0004090</ID><SYNONYM><LITERAL>ochiq<SENSE>13</SENSE></LITERAL></SYNONYM><POS>a</POS><DEF>Dengizning qirg'oqdan uzoqroq joyi</DEF><EXAMPLE>Limanda bilinen gemiler, oysa açıklardadır.</EXAMPLE></SYNSET>
<SYNSET><ID>TUR10-0004430</ID><SYNONYM><LITERAL>ochiq ko'ngilli<SENSE>1</SENSE></LITERAL></SYNONYM><POS>a</POS><ILR>ENG31-00287444-a<TYPE>SYNONYM</TYPE></ILR><DEF>Voqealar va ayniqsa yangiliklarni yaxshi tushuna oladigan va ular bilan to'g'ri uchrasha oladigan, nima deb o'ylasa, shunday deb ayta oladigan odam.</DEF></SYNSET>
<SYNSET><ID>TUR10-0004460</ID><SYNONYM><LITERAL>pishiq<SENSE>1</SENSE></LITERAL><LITERAL>anaç<SENSE>4</SENSE></LITERAL><LITERAL>aynagöz<SENSE>1</SENSE></LITERAL><LITERAL>bitirmiş<SENSE>2</SENSE></LITERAL><LITERAL>cingöz<SENSE>1</SENSE></LITERAL><LITERAL>güllabi<SENSE>2</SENSE></LITERAL><LITERAL>hinoğlu<SENSE>1</SENSE></LITERAL><LITERAL>hinoğluhin<SENSE>1</SENSE></LITERAL><LITERAL>kurnaz<SENSE>1</SENSE></LITERAL><LITERAL>jandarma<SENSE>3</SENSE></LITERAL><LITERAL>malın gözü<SENSE>2</SENSE></LITERAL><LITERAL>uyanık<SENSE>2</SENSE></LITERAL></SYNONYM><POS>a</POS><SR>TUR10-0345060<TYPE>DERIVATION_RELATED</TYPE></SR><SR>TUR10-0141420<TYPE>DERIVATION_RELATED</TYPE></SR><SR>TUR10-0492950<TYPE>DERIVATION_RELATED</TYPE></SR><SR>TUR10-0492990<TYPE>DERIVATION_RELATED</TYPE></SR><SR>TUR10-0493000<TYPE>DERIVATION_RELATED</TYPE></SR><SR>TUR10-0800460<TYPE>DERIVATION_RELATED</TYPE></SR><SR>TUR10-1049200<TYPE>DERIVATION_RELATED</TYPE></SR><SR>TUR10-0072340<TYPE>DERIVATION_RELATED</TYPE></SR><SR>TUR10-0034160<TYPE>DERIVATION_RELATED</TYPE></SR><SR>TUR10-0391080<TYPE>DERIVATION_RELATED</TYPE></SR><SR>TUR10-0801390<TYPE>DERIVATION_RELATED</TYPE></SR><DEF>Hushyor bo'lish kimga foyda keltiradi, kim imkoniyatlardan nozik foydalanishni biladi</DEF></SYNSET>
<SYNSET><ID>TUR10-0004500</ID><SYNONYM><LITERAL>Ochiq kulrang<SENSE>2</SENSE></LITERAL></SYNONYM><POS>a</POS><DEF>ochiq kul rang</DEF></SYNSET>
<SYNSET><ID>TUR10-0004610</ID><SYNONYM><LITERAL>yorqin jigarrang<SENSE>2</SENSE></LITERAL></SYNONYM><POS>a</POS><DEF>ochiq jigarrang rang</DEF></SYNSET>
<SYNSET><ID>TUR10-0004630</ID><SYNONYM><LITERAL>dili ochiq<SENSE>1</SENSE></LITERAL><LITERAL>açık kalpli<SENSE>1</SENSE></LITERAL></SYNONYM><POS>a</POS><ILR>ENG31-01375875-s<TYPE>SYNONYM</TYPE></ILR><DEF>O'ylaganini o'zi kabi aytadigan, ichi toza, sirsiz, samimiy odam</DEF><EXAMPLE>Açık kalpli olmamak çağ dışı bir tutum olur.</EXAMPLE></SYNSET>
<SYNSET><ID>TUR10-0004690</ID><SYNONYM><LITERAL>engil kashtan<SENSE>2</SENSE></LITERAL></SYNONYM><POS>a</POS><DEF>och kashtan rang</DEF></SYNSET>
<SYNSET><ID>TUR10-0004710</ID><SYNONYM><LITERAL>och qizil<SENSE>2</SENSE></LITERAL></SYNONYM><POS>a</POS><DEF>och qizil rang</DEF></SYNSET>
<SYNSET><ID>TUR10-0005240</ID><SYNONYM><LITERAL>och pushti<SENSE>2</SENSE></LITERAL></SYNONYM><POS>a</POS><DEF>och pushti rang</DEF></SYNSET>
<SYNSET><ID>TUR10-0005300</ID><SYNONYM><LITERAL>irqiy<SENSE>2</SENSE></LITERAL></SYNONYM><POS>a</POS><ILR>ENG31-02139604-s<TYPE>SYNONYM</TYPE></ILR><DEF>Sharmandali, yoqimsiz, odobsiz, shahvoniy ma'noga ega so'z, ifoda</DEF></SYNSET>
<SYNSET><ID>TUR10-0005330</ID><SYNONYM><LITERAL>och sariq<SENSE>2</SENSE></LITERAL></SYNONYM><POS>a</POS><DEF>och sariq rang</DEF></SYNSET>
<SYNSET><ID>TUR10-0005350</ID><SYNONYM><LITERAL>aniq<SENSE>1</SENSE></LITERAL></SYNONYM><POS>a</POS><DEF>Juda aniq, juda aniq</DEF></SYNSET>
<SYNSET><ID>TUR10-0005390</ID><SYNONYM><LITERAL>dangalchi<SENSE>1</SENSE></LITERAL></SYNONYM><POS>a</POS><ILR>ENG31-00768027-s<TYPE>SYNONYM</TYPE></ILR><DEF>Hamma narsani boricha aytib berish, uning so'zini ayamaslik</DEF><EXAMPLE>Bu kadar açık sözlü oluşu beni şaşırtmıştı ama belli etmedim.</EXAMPLE></SYNSET>
<SYNSET><ID>TUR10-0005540</ID><SYNONYM><LITERAL>och yashil<SENSE>2</SENSE></LITERAL></SYNONYM><POS>a</POS><DEF>och yashil rang</DEF></SYNSET>
<SYNSET><ID>TUR10-0006970</ID><SYNONYM><LITERAL>bag'ishlangan<SENSE>1</SENSE></LITERAL></SYNONYM><POS>a</POS><SR>TUR10-0006920<TYPE>DERIVATION_RELATED</TYPE></SR><DEF>bag'ishlangan</DEF></SYNSET>
<SYNSET><ID>TUR10-0006980</ID><SYNONYM><LITERAL>bag'ishlangan<SENSE>2</SENSE></LITERAL></SYNONYM><POS>a</POS><DEF>Unashtirilgan</DEF></SYNSET>
<SYNSET><ID>TUR10-0007000</ID><SYNONYM><LITERAL>bag'ishlanish<SENSE>2</SENSE></LITERAL></SYNONYM><POS>a</POS><SR>TUR10-0576280<TYPE>DERIVATION_RELATED</TYPE></SR><DEF>Bag'ishlangan hayvon</DEF></SYNSET>
<SYNSET><ID>TUR10-0007020</ID><SYNONYM><LITERAL>bag'ishlanmagan<SENSE>1</SENSE></LITERAL></SYNONYM><POS>a</POS><SR>TUR10-0006920<TYPE>DERIVATION_RELATED</TYPE></SR><DEF>qasam ichmaganlar</DEF></SYNSET>
<SYNSET><ID>TUR10-0007030</ID><SYNONYM><LITERAL>unashtirilmagan<SENSE>2</SENSE></LITERAL></SYNONYM><POS>a</POS><DEF>Unashtirilmagan</DEF></SYNSET>
<SYNSET><ID>TUR10-0007050</ID><SYNONYM><LITERAL>baquvvat<SENSE>1</SENSE></LITERAL><LITERAL>adaleli<SENSE>1</SENSE></LITERAL></SYNONYM><POS>a</POS><ILR>ENG31-02329581-s<TYPE>SYNONYM</TYPE></ILR><SR>TUR10-0424410<TYPE>DERIVATION_RELATED</TYPE></SR><DEF>Mushaklar qattiq, rivojlangan</DEF><EXAMPLE>İki kolunu da yukarı kadar sıvadı, sert adaleli kollarını meydana çıkardı.</EXAMPLE></SYNSET>
<SYNSET><ID>TUR10-0007060</ID><SYNONYM><LITERAL>nimjon<SENSE>1</SENSE></LITERAL><LITERAL>adalesiz<SENSE>1</SENSE></LITERAL></SYNONYM><POS>a</POS><SR>TUR10-0424410<TYPE>DERIVATION_RELATED</TYPE></SR><DEF>Kimning mushaklari rivojlanmagan</DEF></SYNSET>
<SYNSET><ID>TUR10-0007180</ID><SYNONYM><LITERAL>adolatsiz<SENSE>1</SENSE></LITERAL></SYNONYM><POS>a</POS><ILR>ENG31-01373517-a<TYPE>SYNONYM</TYPE></ILR><SR>TUR10-0007070<TYPE>DERIVATION_RELATED</TYPE></SR><SR>TUR10-0007090<TYPE>DERIVATION_RELATED</TYPE></SR><SR>TUR10-0007100<TYPE>DERIVATION_RELATED</TYPE></SR><DEF>Adolatsiz yoki adolatsiz</DEF></SYNSET>
<SYNSET><ID>TUR10-0007200</ID><SYNONYM><LITERAL>orollik<SENSE>1</SENSE></LITERAL></SYNONYM><POS>a</POS><SR>TUR10-0138060<TYPE>DERIVATION_RELATED</TYPE></SR><DEF>Orol davlatidan (hech kim)</DEF></SYNSET>
<SYNSET><ID>TUR10-0007490</ID><SYNONYM><LITERAL>erkakcha<SENSE>1</SENSE></LITERAL></SYNONYM><POS>a</POS><SR>TUR10-0932620<TYPE>DERIVATION_RELATED</TYPE></SR><DEF>Odamlardan qo'rqmaydi, odamlarga o'rganib qolgan, odamlarga tanish, iliq qonli, mujizlar</DEF><EXAMPLE>Hem de ne adamcıldır, ne candır, bilseniz.</EXAMPLE></SYNSET>
<SYNSET><ID>TUR10-0007590</ID><SYNONYM><LITERAL>odamsiz<SENSE>1</SENSE></LITERAL></SYNONYM><POS>a</POS><DEF>Yordam yo'q, xizmatkor yo'q</DEF></SYNSET>
<SYNSET><ID>TUR10-0007610</ID><SYNONYM><LITERAL>ersiz<SENSE>1</SENSE></LITERAL><LITERAL>adamsız<SENSE>3</SENSE></LITERAL><LITERAL>ersiz<SENSE>1</SENSE></LITERAL><LITERAL>erkeksiz<SENSE>1</SENSE></LITERAL></SYNONYM><POS>a</POS><SR>TUR10-0251130<TYPE>DERIVATION_RELATED</TYPE></SR><SR>TUR10-0465480<TYPE>DERIVATION_RELATED</TYPE></SR><DEF>Ersiz ayol</DEF><EXAMPLE>Erkeksiz ev.</EXAMPLE></SYNSET>
<SYNSET><ID>TUR10-0007740</ID><SYNONYM><LITERAL>moslashadigan<SENSE>1</SENSE></LITERAL><LITERAL>uyarlama<SENSE>3</SENSE></LITERAL></SYNONYM><POS>a</POS><DEF>Moslashtirildi</DEF><EXAMPLE>Ahmet Vefik Paşa'nın Zor Nikâh'ı Molière'den adaptedir.</EXAMPLE></SYNSET>
<SYNSET><ID>TUR10-0008420</ID><SYNONYM><LITERAL>notanish<SENSE>1</SENSE></LITERAL></SYNONYM><POS>a</POS><DEF>Kim va nima noma'lum, noma'lum, noma'lum</DEF></SYNSET>
<SYNSET><ID>TUR10-0008560</ID><SYNONYM><LITERAL>qadamli<SENSE>1</SENSE></LITERAL></SYNONYM><POS>a</POS><DEF>Qadam uzunligi</DEF><EXAMPLE>Ayak basacak tek adımlık temiz yer yok.</EXAMPLE></SYNSET>
<SYNSET><ID>TUR10-0008620</ID><SYNONYM><LITERAL>oddiy<SENSE>1</SENSE></LITERAL><LITERAL>aşağı<SENSE>4</SENSE></LITERAL><LITERAL>dun<SENSE>1</SENSE></LITERAL></SYNONYM><POS>a</POS><ILR>ENG31-02354508-s<TYPE>SYNONYM</TYPE></ILR><SR>TUR10-0008700<TYPE>DERIVATION_RELATED</TYPE></SR><SR>TUR10-0085980<TYPE>DERIVATION_RELATED</TYPE></SR><SR>TUR10-0008630<TYPE>DERIVATION_RELATED</TYPE></SR><SR>TUR10-0052120<TYPE>DERIVATION_RELATED</TYPE></SR><SR>TUR10-0052130<TYPE>DERIVATION_RELATED</TYPE></SR><SR>TUR10-0052180<TYPE>DERIVATION_RELATED</TYPE></SR><SR>TUR10-0378220<TYPE>DERIVATION_RELATED</TYPE></SR><SR>TUR10-0885630<TYPE>DERIVATION_RELATED</TYPE></SR><SR>TUR10-0942500<TYPE>DERIVATION_RELATED</TYPE></SR><SR>TUR10-0942550<TYPE>DERIVATION_RELATED</TYPE></SR><DEF>Arzimaydi, yomon, oddiy, alohida narsa yo'q</DEF><EXAMPLE>Sonra redingot devri geldi ve redingot içinden yarı uşak, yarı kapı kulu, riyakâr, adi bir nesil türedi.</EXAMPLE></SYNSET>
<SYNSET><ID>TUR10-0008630</ID><SYNONYM><LITERAL>pastkash<SENSE>2</SENSE></LITERAL><LITERAL>aşağılık<SENSE>2</SENSE></LITERAL></SYNONYM><POS>a</POS><ILR>ENG31-01231032-s<TYPE>SYNONYM</TYPE></ILR><SR>TUR10-0008700<TYPE>DERIVATION_RELATED</TYPE></SR><SR>TUR10-0085980<TYPE>DERIVATION_RELATED</TYPE></SR><SR>TUR10-0008620<TYPE>DERIVATION_RELATED</TYPE></SR><SR>TUR10-0052070<TYPE>DERIVATION_RELATED</TYPE></SR><SR>TUR10-0052090<TYPE>DERIVATION_RELATED</TYPE></SR><DEF>Chiroyli, past sifatli</DEF><EXAMPLE>Bazen en aşağılık bir romanı tabii olarak okur.</EXAMPLE></SYNSET>
<SYNSET><ID>TUR10-0008670</ID><SYNONYM><LITERAL>odil<SENSE>1</SENSE></LITERAL><LITERAL>adaletli<SENSE>1</SENSE></LITERAL><LITERAL>âdil<SENSE>1</SENSE></LITERAL></SYNONYM><POS>a</POS><ILR>ENG31-00959321-a<TYPE>SYNONYM</TYPE></ILR><SR>TUR10-0322140<TYPE>ANTONYM</TYPE></SR><SR>TUR10-0007100<TYPE>DERIVATION_RELATED</TYPE></SR><SR>TUR10-0008930<TYPE>DERIVATION_RELATED</TYPE></SR><SR>TUR10-0321420<TYPE>DERIVATION_RELATED</TYPE></SR><SR>TUR10-0428480<TYPE>DERIVATION_RELATED</TYPE></SR><SR>TUR10-0007070<TYPE>DERIVATION_RELATED</TYPE></SR><SR>TUR10-0007080<TYPE>DERIVATION_RELATED</TYPE></SR><SR>TUR10-0007090<TYPE>DERIVATION_RELATED</TYPE></SR><DEF>Adolat bilan muomala qilish, adolat va adolatni tark etmaslik, haqni bajarish</DEF><EXAMPLE>Milletler tarihte fatihlerden fazla adillere bağlıdırlar.</EXAMPLE></SYNSET>
<SYNSET><ID>TUR10-0008900</ID><SYNONYM><LITERAL>yuridik<SENSE>1</SENSE></LITERAL></SYNONYM><POS>a</POS><SR>TUR10-0006800<TYPE>DERIVATION_RELATED</TYPE></SR><SR>TUR10-0379560<TYPE>DERIVATION_RELATED</TYPE></SR><DEF>nomlangan</DEF><EXAMPLE>Geçen gün 'Kayıp Mektup' adlı oyunu ikinci kez gördüm.</EXAMPLE></SYNSET>
<SYNSET><ID>TUR10-0008910</ID><SYNONYM><LITERAL>mashhur<SENSE>1</SENSE></LITERAL><LITERAL>adlı<SENSE>2</SENSE></LITERAL><LITERAL>adlı sanlı<SENSE>1</SENSE></LITERAL><LITERAL>namdar<SENSE>1</SENSE></LITERAL><LITERAL>sanlı<SENSE>1</SENSE></LITERAL><LITERAL>tanınmış<SENSE>1</SENSE></LITERAL><LITERAL>namlı<SENSE>1</SENSE></LITERAL><LITERAL>ünlü<SENSE>1</SENSE></LITERAL><LITERAL>şöhretli<SENSE>1</SENSE></LITERAL><LITERAL>maruf<SENSE>1</SENSE></LITERAL><LITERAL>şanlı<SENSE>1</SENSE></LITERAL></SYNONYM><POS>a</POS><ILR>ENG31-01378757-s<TYPE>SYNONYM</TYPE></ILR><SR>TUR10-0733660<TYPE>DERIVATION_RELATED</TYPE></SR><SR>TUR10-0282080<TYPE>DERIVATION_RELATED</TYPE></SR><SR>TUR10-0527100<TYPE>DERIVATION_RELATED</TYPE></SR><SR>TUR10-0538880<TYPE>DERIVATION_RELATED</TYPE></SR><SR>TUR10-0006790<TYPE>DERIVATION_RELATED</TYPE></SR><DEF>Hammaga ma'lum, ma'lum, taniqli, mashhur</DEF><EXAMPLE>Memleketin tanınmış bir hekimi.</EXAMPLE></SYNSET>
<SYNSET><ID>TUR10-0008930</ID><SYNONYM><LITERAL>huquqiy<SENSE>1</SENSE></LITERAL><LITERAL>adlî<SENSE>1</SENSE></LITERAL></SYNONYM><POS>a</POS><SR>TUR10-0349630<TYPE>DOMAIN_TOPIC</TYPE></SR><ILR>ENG31-02763759-a<TYPE>SYNONYM</TYPE></ILR><SR>TUR10-0008670<TYPE>DERIVATION_RELATED</TYPE></SR><SR>TUR10-0009060<TYPE>DERIVATION_RELATED</TYPE></SR><SR>TUR10-0009070<TYPE>DERIVATION_RELATED</TYPE></SR><SR>TUR10-0009080<TYPE>DERIVATION_RELATED</TYPE></SR><DEF>Adolat to'g'risida</DEF><EXAMPLE>Eğer insan tedbiri olarak herhangi bir ihmal veya kötü kasta dayanıyorsa o zaman da adli hata olmaktan çıkar, zulüm olur.</EXAMPLE></SYNSET>
<SYNSET><ID>TUR10-0009230</ID><SYNONYM><LITERAL>nomsiz<SENSE>1</SENSE></LITERAL><LITERAL>isimsiz<SENSE>2</SENSE></LITERAL></SYNONYM><POS>a</POS><ILR>ENG31-00121594-s<TYPE>SYNONYM</TYPE></ILR><SR>TUR10-0379560<TYPE>DERIVATION_RELATED</TYPE></SR><SR>TUR10-0733660<TYPE>DERIVATION_RELATED</TYPE></SR><DEF>Garchi uning ishi ma'lum bo'lsa ham, o'zi noma'lum</DEF></SYNSET>
<SYNSET><ID>TUR10-0009280</ID><SYNONYM><LITERAL>benom<SENSE>1</SENSE></LITERAL></SYNONYM><POS>a</POS><DEF>Noma'lum, noma'lum</DEF><EXAMPLE>Yıllarca bir köşede adsız sansız, bir yarım münevver ömrü sürmeye mahkûm kalmanın acısı yüreğini hınç ve isyan ile doldurmuş.</EXAMPLE></SYNSET>
<SYNSET><ID>TUR10-0009330</ID><SYNONYM><LITERAL>aerodinamik<SENSE>2</SENSE></LITERAL></SYNONYM><POS>a</POS><SR>TUR10-0199630<TYPE>DERIVATION_RELATED</TYPE></SR><DEF>Havoning harakatdagi ob'ektga ta'sirini o'rganadigan fan sohasi bilan bog'liq.</DEF></SYNSET>
<SYNSET><ID>TUR10-0009360</ID><SYNONYM><LITERAL>aerologik<SENSE>1</SENSE></LITERAL></SYNONYM><POS>a</POS><DEF>aerologiya</DEF></SYNSET>
<SYNSET><ID>TUR10-0009450</ID><SYNONYM><LITERAL>oldi-qochdi<SENSE>1</SENSE></LITERAL></SYNONYM><POS>a</POS><DEF>Muayyan mavzuda emas, balki yuqoridan gapirish</DEF></SYNSET>
<SYNSET><ID>TUR10-0009480</ID><SYNONYM><LITERAL>dovdir<SENSE>1</SENSE></LITERAL></SYNONYM><POS>a</POS><SR>TUR10-0009520<TYPE>DERIVATION_RELATED</TYPE></SR><SR>TUR10-0119840<TYPE>DERIVATION_RELATED</TYPE></SR><DEF>Sarosimaga tushgan, tartibsiz, nima qilishni bilmayman</DEF><EXAMPLE>Bir top ağzından henüz fırlamış gibi afal ve dağınıktı.</EXAMPLE></SYNSET>
<SYNSET><ID>TUR10-0009640</ID><SYNONYM><LITERAL>ofat<SENSE>3</SENSE></LITERAL><LITERAL>felaket<SENSE>2</SENSE></LITERAL></SYNONYM><POS>a</POS><ILR>ENG31-01165179-s<TYPE>SYNONYM</TYPE></ILR><DEF>Juda yomon</DEF><EXAMPLE>Şöhret gibi servetin de afet olduğunu yeni anlıyordum.</EXAMPLE></SYNSET>
<SYNSET><ID>TUR10-0009830</ID><SYNONYM><LITERAL>Afg'on<SENSE>2</SENSE></LITERAL></SYNONYM><POS>a</POS><SR>TUR10-1195270<TYPE>DERIVATION_RELATED</TYPE></SR><DEF>Afg'oniston va Afg'oniston xalqi uchun noyobdir</DEF></SYNSET>
<SYNSET><ID>TUR10-0009850</ID><SYNONYM><LITERAL>iffatli<SENSE>1</SENSE></LITERAL></SYNONYM><POS>a</POS><DEF>Odobli odam</DEF></SYNSET>
<SYNSET><ID>TUR10-0009870</ID><SYNONYM><LITERAL>dimog'dorona<SENSE>1</SENSE></LITERAL><LITERAL>alengirli<SENSE>1</SENSE></LITERAL><LITERAL>façalı<SENSE>1</SENSE></LITERAL><LITERAL>lüks<SENSE>2</SENSE></LITERAL><LITERAL>alımlı çalımlı<SENSE>1</SENSE></LITERAL><LITERAL>alayişli<SENSE>1</SENSE></LITERAL><LITERAL>fosforlu<SENSE>3</SENSE></LITERAL><LITERAL>görklü<SENSE>1</SENSE></LITERAL><LITERAL>çalımlı<SENSE>1</SENSE></LITERAL><LITERAL>alaylı<SENSE>4</SENSE></LITERAL><LITERAL>anıtsal<SENSE>2</SENSE></LITERAL><LITERAL>debdebeli<SENSE>1</SENSE></LITERAL><LITERAL>azametli<SENSE>4</SENSE></LITERAL><LITERAL>gösterişli<SENSE>1</SENSE></LITERAL><LITERAL>haşmetli<SENSE>1</SENSE></LITERAL><LITERAL>muhteşem<SENSE>1</SENSE></LITERAL><LITERAL>anlı şanlı<SENSE>1</SENSE></LITERAL><LITERAL>mutantan<SENSE>1</SENSE></LITERAL><LITERAL>saltanatlı<SENSE>1</SENSE></LITERAL><LITERAL>şaşaalı<SENSE>1</SENSE></LITERAL><LITERAL>şatafatlı<SENSE>1</SENSE></LITERAL><LITERAL>sunturlu<SENSE>2</SENSE></LITERAL><LITERAL>tantanalı<SENSE>1</SENSE></LITERAL><LITERAL>zengin<SENSE>4</SENSE></LITERAL><LITERAL>bomba gibi<SENSE>1</SENSE></LITERAL><LITERAL>oturaklı<SENSE>1</SENSE></LITERAL></SYNONYM><POS>a</POS><SR>TUR10-0009840<TYPE>DERIVATION_RELATED</TYPE></SR><SR>TUR10-0024750<TYPE>DERIVATION_RELATED</TYPE></SR><SR>TUR10-0064530<TYPE>DERIVATION_RELATED</TYPE></SR><SR>TUR10-0661470<TYPE>DERIVATION_RELATED</TYPE></SR><SR>TUR10-0001110<TYPE>DERIVATION_RELATED</TYPE></SR><SR>TUR10-0010260<TYPE>DERIVATION_RELATED</TYPE></SR><SR>TUR10-0036990<TYPE>DERIVATION_RELATED</TYPE></SR><SR>TUR10-0307160<TYPE>DERIVATION_RELATED</TYPE></SR><SR>TUR10-0307190<TYPE>DERIVATION_RELATED</TYPE></SR><DEF>O'zining kattaligi, tashqi ko'rinishi yoki go'zalligi bilan ko'rganlarga ta'sir qilish</DEF></SYNSET>
<SYNSET><ID>TUR10-0009920</ID><SYNONYM><LITERAL>e'lon qilingan<SENSE>1</SENSE></LITERAL></SYNONYM><POS>a</POS><SR>TUR10-0009890<TYPE>DERIVATION_RELATED</TYPE></SR><DEF>Fosh qilindi, eshitildi</DEF></SYNSET>
<SYNSET><ID>TUR10-0010060</ID><SYNONYM><LITERAL>quvib chiqarilgan<SENSE>1</SENSE></LITERAL></SYNONYM><POS>a</POS><SR>TUR10-1163150<TYPE>DERIVATION_RELATED</TYPE></SR><DEF>Chetlatilgan, haydalgan, quvilgan</DEF><EXAMPLE>Demek kahraman tabiatlılar aforozluydular.</EXAMPLE></SYNSET>
<SYNSET><ID>TUR10-0010070</ID><SYNONYM><LITERAL>dimog'dorlik bilan<SENSE>1</SENSE></LITERAL></SYNONYM><POS>a</POS><DEF>Chalmalı</DEF></SYNSET>
<SYNSET><ID>TUR10-0010360</ID><SYNONYM><LITERAL>afyunli<SENSE>1</SENSE></LITERAL></SYNONYM><POS>a</POS><SR>TUR10-0010270<TYPE>DERIVATION_RELATED</TYPE></SR><DEF>Ichida afyun bor</DEF></SYNSET>
<SYNSET><ID>TUR10-0010370</ID><SYNONYM><LITERAL>afyunli<SENSE>2</SENSE></LITERAL></SYNONYM><POS>a</POS><SR>TUR10-0010270<TYPE>DERIVATION_RELATED</TYPE></SR><DEF>Afyun yutildi</DEF></SYNSET>
<SYNSET><ID>TUR10-0010380</ID><SYNONYM><LITERAL>afyunli<SENSE>3</SENSE></LITERAL></SYNONYM><POS>a</POS><SR>TUR10-0010270<TYPE>DERIVATION_RELATED</TYPE></SR><DEF>Pensiv, uyqusiz, sust</DEF></SYNSET>
<SYNSET><ID>TUR10-0010500</ID><SYNONYM><LITERAL>agnostik<SENSE>2</SENSE></LITERAL></SYNONYM><POS>a</POS><SR>TUR10-0267320<TYPE>DOMAIN_TOPIC</TYPE></SR><DEF>Agnostik bo'yicha</DEF></SYNSET>
<SYNSET><ID>TUR10-0010620</ID><SYNONYM><LITERAL>tajovuzkor<SENSE>1</SENSE></LITERAL><LITERAL>kuduruk<SENSE>2</SENSE></LITERAL><LITERAL>tecavüzkar<SENSE>1</SENSE></LITERAL><LITERAL>tecavüzkâr<SENSE>1</SENSE></LITERAL><LITERAL>mütecaviz<SENSE>1</SENSE></LITERAL><LITERAL>pençeli<SENSE>4</SENSE></LITERAL><LITERAL>sataşkan<SENSE>1</SENSE></LITERAL><LITERAL>saldırıcı<SENSE>1</SENSE></LITERAL><LITERAL>saldırgan<SENSE>1</SENSE></LITERAL></SYNONYM><POS>a</POS><SR>TUR10-0668070<TYPE>DERIVATION_RELATED</TYPE></SR><SR>TUR10-0488010<TYPE>DERIVATION_RELATED</TYPE></SR><SR>TUR10-0488020<TYPE>DERIVATION_RELATED</TYPE></SR><SR>TUR10-0488030<TYPE>DERIVATION_RELATED</TYPE></SR><SR>TUR10-0622550<TYPE>DERIVATION_RELATED</TYPE></SR><SR>TUR10-0659820<TYPE>DERIVATION_RELATED</TYPE></SR><SR>TUR10-0659830<TYPE>DERIVATION_RELATED</TYPE></SR><SR>TUR10-1246060<TYPE>DERIVATION_RELATED</TYPE></SR><DEF>Birovga hujum qilgan davlat, odam, hayvon hujum qilish qobiliyatiga ega,</DEF></SYNSET>
<SYNSET><ID>TUR10-0010840</ID><SYNONYM><LITERAL>bobo<SENSE>2</SENSE></LITERAL></SYNONYM><POS>a</POS><SR>TUR10-0010770<TYPE>DERIVATION_RELATED</TYPE></SR><SR>TUR10-0010780<TYPE>DERIVATION_RELATED</TYPE></SR><DEF>Bir joyda, jamoada, ta'sirchan, eslatib o'tilgan, taniqli</DEF></SYNSET>
<SYNSET><ID>TUR10-0010910</ID><SYNONYM><LITERAL>yog'och<SENSE>2</SENSE></LITERAL></SYNONYM><POS>a</POS><SR>TUR10-0109440<TYPE>DOMAIN_TOPIC</TYPE></SR><ILR>ENG31-02586927-s<TYPE>SYNONYM</TYPE></ILR><SR>TUR10-0011340<TYPE>DERIVATION_RELATED</TYPE></SR><SR>TUR10-0430100<TYPE>DERIVATION_RELATED</TYPE></SR><SR>TUR10-0482490<TYPE>DERIVATION_RELATED</TYPE></SR><SR>TUR10-0882430<TYPE>DERIVATION_RELATED</TYPE></SR><DEF>Meva bera oladigan, tanasi yog'och yoki yog'ochga yaroqli bo'lgan va ko'p yillar yashashi mumkin bo'lgan o'simliklarning tanasi va shoxlaridan qilingan.</DEF><EXAMPLE>Ağaç tekne.</EXAMPLE></SYNSET>
<SYNSET><ID>TUR10-0011200</ID><SYNONYM><LITERAL>yog'ochli<SENSE>1</SENSE></LITERAL></SYNONYM><POS>a</POS><SR>TUR10-0010900<TYPE>DERIVATION_RELATED</TYPE></SR><DEF>daraxt bilan</DEF><EXAMPLE>İki yanı ağaçlı yol ta dış kapıya kadar uzayıp gidiyordu.</EXAMPLE></SYNSET>
<SYNSET><ID>TUR10-0011230</ID><SYNONYM><LITERAL>o'rmonli<SENSE>1</SENSE></LITERAL></SYNONYM><POS>a</POS><SR>TUR10-0010900<TYPE>DERIVATION_RELATED</TYPE></SR><DEF>Ko'p daraxtlar bo'lgan joy</DEF></SYNSET>
<SYNSET><ID>TUR10-0011350</ID><SYNONYM><LITERAL>yog'ochsiz<SENSE>1</SENSE></LITERAL></SYNONYM><POS>a</POS><SR>TUR10-0010900<TYPE>DERIVATION_RELATED</TYPE></SR><DEF>daraxtsiz</DEF></SYNSET>
<SYNSET><ID>TUR10-0011430</ID><SYNONYM><LITERAL>oqartirilgan<SENSE>1</SENSE></LITERAL></SYNONYM><POS>a</POS><SR>TUR10-0011460<TYPE>DERIVATION_RELATED</TYPE></SR><SR>TUR10-0011470<TYPE>DERIVATION_RELATED</TYPE></SR><DEF>Oq, rangi o'chgan</DEF></SYNSET>
<SYNSET><ID>TUR10-0011750</ID><SYNONYM><LITERAL>yopishqoq<SENSE>1</SENSE></LITERAL></SYNONYM><POS>a</POS><SR>TUR10-0011630<TYPE>DERIVATION_RELATED</TYPE></SR><DEF>Mumlangan</DEF></SYNSET>
<SYNSET><ID>TUR10-0011760</ID><SYNONYM><LITERAL>yopishqoq<SENSE>2</SENSE></LITERAL></SYNONYM><POS>a</POS><ILR>ENG31-00552046-s<TYPE>SYNONYM</TYPE></ILR><DEF>Noma'lum so'zlardan, tushunarsiz, bo'g'iq jumlalardan tashkil topgan ibora</DEF></SYNSET>
<SYNSET><ID>TUR10-0012080</ID><SYNONYM><LITERAL>og'ir<SENSE>1</SENSE></LITERAL></SYNONYM><POS>a</POS><SR>TUR10-0846330<TYPE>ANTONYM</TYPE></SR><ILR>ENG31-01188475-a<TYPE>SYNONYM</TYPE></ILR><SR>TUR10-0077920<TYPE>DERIVATION_RELATED</TYPE></SR><SR>TUR10-0080800<TYPE>DERIVATION_RELATED</TYPE></SR><SR>TUR10-0592610<TYPE>DERIVATION_RELATED</TYPE></SR><SR>TUR10-0694500<TYPE>DERIVATION_RELATED</TYPE></SR><SR>TUR10-0794790<TYPE>DERIVATION_RELATED</TYPE></SR><SR>TUR10-0922730<TYPE>DERIVATION_RELATED</TYPE></SR><SR>TUR10-1250850<TYPE>DERIVATION_RELATED</TYPE></SR><SR>TUR10-1253790<TYPE>DERIVATION_RELATED</TYPE></SR><DEF>Miqyosga juda jalb qilingan</DEF></SYNSET>
<SYNSET><ID>TUR10-0012090</ID><SYNONYM><LITERAL>og'ir<SENSE>2</SENSE></LITERAL></SYNONYM><POS>a</POS><ILR>ENG31-00037111-s<TYPE>SYNONYM</TYPE></ILR><ILR>ENG31-01192034-s<TYPE>SYNONYM</TYPE></ILR><ILR>ENG31-01194226-a<TYPE>SYNONYM</TYPE></ILR><ILR>ENG31-02420355-s<TYPE>SYNONYM</TYPE></ILR><SR>TUR10-0013160<TYPE>DERIVATION_RELATED</TYPE></SR><DEF>Qiymat uchun ajoyib, yorqin</DEF><EXAMPLE>Ağır kıyafeti ile muhite uymayan Canan'ın yanında, ne kadar rahat ve sadeydi.</EXAMPLE></SYNSET>
<SYNSET><ID>TUR10-0012100</ID><SYNONYM><LITERAL>og'ir<SENSE>3</SENSE></LITERAL></SYNONYM><POS>a</POS><SR>TUR10-0077920<TYPE>DERIVATION_RELATED</TYPE></SR><DEF>Katta diametr, o'lchamlar</DEF></SYNSET>
<SYNSET><ID>TUR10-0012110</ID><SYNONYM><LITERAL>og'ir<SENSE>4</SENSE></LITERAL><LITERAL>çetin<SENSE>1</SENSE></LITERAL><LITERAL>çetince<SENSE>1</SENSE></LITERAL><LITERAL>müşkül<SENSE>1</SENSE></LITERAL><LITERAL>yavuz<SENSE>2</SENSE></LITERAL></SYNONYM><POS>a</POS><SR>TUR10-0160740<TYPE>DERIVATION_RELATED</TYPE></SR><SR>TUR10-0160810<TYPE>DERIVATION_RELATED</TYPE></SR><SR>TUR10-0445300<TYPE>DERIVATION_RELATED</TYPE></SR><SR>TUR10-0565500<TYPE>DERIVATION_RELATED</TYPE></SR><SR>TUR10-0565540<TYPE>DERIVATION_RELATED</TYPE></SR><SR>TUR10-0877520<TYPE>DERIVATION_RELATED</TYPE></SR><SR>TUR10-1017160<TYPE>DERIVATION_RELATED</TYPE></SR><SR>TUR10-0842320<TYPE>DERIVATION_RELATED</TYPE></SR><SR>TUR10-0842350<TYPE>DERIVATION_RELATED</TYPE></SR><DEF>Belgilangan holatga keltirish, olish, tahlil qilish, qayta ishlash yoki ko'plab to'siqlarga ega bo'lish qiyin, qiyin</DEF></SYNSET>
<SYNSET><ID>TUR10-0012130</ID><SYNONYM><LITERAL>og'ir<SENSE>6</SENSE></LITERAL></SYNONYM><POS>a</POS><ILR>ENG31-01194226-a<TYPE>SYNONYM</TYPE></ILR><SR>TUR10-0320330<TYPE>ANTONYM</TYPE></SR><DEF>Muammo, juda katta</DEF></SYNSET>
<SYNSET><ID>TUR10-0012140</ID><SYNONYM><LITERAL>og'ir<SENSE>7</SENSE></LITERAL></SYNONYM><POS>a</POS><DEF>Teginish, insonning kuchiga o'tish, shikast etkazish</DEF><EXAMPLE>Kızmıştım, Keziban'a söylenecek şöyle ağır bir söz arıyordum.</EXAMPLE></SYNSET>
<SYNSET><ID>TUR10-0012150</ID><SYNONYM><LITERAL>obro'li<SENSE>1</SENSE></LITERAL><LITERAL>ağır<SENSE>8</SENSE></LITERAL><LITERAL>ciddi<SENSE>2</SENSE></LITERAL><LITERAL>vakarlı<SENSE>1</SENSE></LITERAL><LITERAL>vakur<SENSE>1</SENSE></LITERAL><LITERAL>vâkur<SENSE>1</SENSE></LITERAL></SYNONYM><POS>a</POS><SR>TUR10-0812890<TYPE>DERIVATION_RELATED</TYPE></SR><SR>TUR10-0140080<TYPE>DERIVATION_RELATED</TYPE></SR><SR>TUR10-0140130<TYPE>DERIVATION_RELATED</TYPE></SR><SR>TUR10-0284710<TYPE>DERIVATION_RELATED</TYPE></SR><DEF>O'rtacha xatti-harakatlar, etuk</DEF></SYNSET>
<SYNSET><ID>TUR10-0012160</ID><SYNONYM><LITERAL>og'ir<SENSE>9</SENSE></LITERAL></SYNONYM><POS>a</POS><DEF>O'tkir, yoqimsiz hid</DEF></SYNSET>
<SYNSET><ID>TUR10-0012170</ID><SYNONYM><LITERAL>og'ir<SENSE>10</SENSE></LITERAL></SYNONYM><POS>a</POS><DEF>Hazm bo'lmaydigan ovqat</DEF></SYNSET>
<SYNSET><ID>TUR10-0012180</ID><SYNONYM><LITERAL>og'ir<SENSE>11</SENSE></LITERAL></SYNONYM><POS>a</POS><SR>TUR10-0013200<TYPE>DERIVATION_RELATED</TYPE></SR><SR>TUR10-1253790<TYPE>DERIVATION_RELATED</TYPE></SR><DEF>Kuchli ta'sir, kuchli</DEF></SYNSET>
<SYNSET><ID>TUR10-0012190</ID><SYNONYM><LITERAL>og'ir<SENSE>12</SENSE></LITERAL></SYNONYM><POS>a</POS><DEF>Uyg'onish qiyin, chuqur uxlash</DEF></SYNSET>
<SYNSET><ID>TUR10-0012200</ID><SYNONYM><LITERAL>og'ir<SENSE>13</SENSE></LITERAL></SYNONYM><POS>a</POS><DEF>Xirillash, past</DEF><EXAMPLE>Ağaya pek duyurmak istemeyen ağır bir sesle kulağıma eğildi.</EXAMPLE></SYNSET>
<SYNSET><ID>TUR10-0012210</ID><SYNONYM><LITERAL>og'ir<SENSE>14</SENSE></LITERAL></SYNONYM><POS>a</POS><DEF>Qattiq eshitish, karlar</DEF></SYNSET>
<SYNSET><ID>TUR10-0012230</ID><SYNONYM><LITERAL>og'ir<SENSE>16</SENSE></LITERAL></SYNONYM><POS>a</POS><ILR>ENG31-00879513-s<TYPE>SYNONYM</TYPE></ILR><SR>TUR10-0012410<TYPE>DERIVATION_RELATED</TYPE></SR><SR>TUR10-1247980<TYPE>DERIVATION_RELATED</TYPE></SR><DEF>Kimlar harakat qilishda sust</DEF></SYNSET>
<SYNSET><ID>TUR10-0012240</ID><SYNONYM><LITERAL>og'ir<SENSE>17</SENSE></LITERAL></SYNONYM><POS>a</POS><SR>TUR10-0708190<TYPE>DOMAIN_TOPIC</TYPE></SR><SR>TUR10-0080800<TYPE>DERIVATION_RELATED</TYPE></SR><DEF>Og'ir vazn</DEF><EXAMPLE>Yıllarca ağırda güreşti.</EXAMPLE></SYNSET>
<SYNSET><ID>TUR10-0012280</ID><SYNONYM><LITERAL>sekin<SENSE>2</SENSE></LITERAL></SYNONYM><POS>a</POS><SR>TUR10-0556740<TYPE>DOMAIN_TOPIC</TYPE></SR><DEF>Sekin</DEF></SYNSET>
<SYNSET><ID>TUR10-0012290</ID><SYNONYM><LITERAL>sekin<SENSE>3</SENSE></LITERAL></SYNONYM><POS>a</POS><SR>TUR10-0556740<TYPE>DOMAIN_TOPIC</TYPE></SR><DEF>Vaqti-vaqti bilan, tartibsiz</DEF></SYNSET>
<SYNSET><ID>TUR10-0012340</ID><SYNONYM><LITERAL>og'ir<SENSE>1</SENSE></LITERAL></SYNONYM><POS>a</POS><DEF>Juda og'ir</DEF><EXAMPLE>Biraz sonra aşağıda bir kapı açıldığı, sonra da ağırca bir şeyin devrildiği duyulur.</EXAMPLE></SYNSET>
<SYNSET><ID>TUR10-0012350</ID><SYNONYM><LITERAL>og'ir<SENSE>2</SENSE></LITERAL></SYNONYM><POS>a</POS><DEF>Bemor yomonlashdi</DEF></SYNSET>
<SYNSET><ID>TUR10-0012370</ID><SYNONYM><LITERAL>og'ir<SENSE>1</SENSE></LITERAL></SYNONYM><POS>a</POS><DEF>Juda sekin, epchil emas</DEF></SYNSET>
<SYNSET><ID>TUR10-0012380</ID><SYNONYM><LITERAL>og'ir<SENSE>2</SENSE></LITERAL></SYNONYM><POS>a</POS><DEF>Uning mavjudligi tashvishga soladigan, yoqimsiz</DEF></SYNSET>
<SYNSET><ID>TUR10-0012390</ID><SYNONYM><LITERAL>og'ir<SENSE>3</SENSE></LITERAL></SYNONYM><POS>a</POS><DEF>Dangasa</DEF></SYNSET>
<SYNSET><ID>TUR10-0012400</ID><SYNONYM><LITERAL>og'ir<SENSE>4</SENSE></LITERAL></SYNONYM><POS>a</POS><DEF>Homilador ayol</DEF></SYNSET>
</SYNSETS>